UDTherapy/__init__.py
UDTherapy/helper.py
UDTherapy-1.0.1.data/scripts/UDTherapy
UDTherapy-1.0.1.dist-info/LICENSE
UDTherapy-1.0.1.dist-info/METADATA
UDTherapy-1.0.1.dist-info/WHEEL
UDTherapy-1.0.1.dist-info/top_level.txt
UDTherapy-1.0.1.dist-info/RECORD
