Metadata-Version: 2.1
Name: UDTherapy
Version: 1.0.1
Summary: A simple rehabilitation program for coping with long days of programming
Home-page: https://github.com/tterb/Urban-Dictionary-Therapy
Author: Brett Stevenson
Author-email: bstevensondev@gmail.com
License: UNKNOWN
Download-URL: https://github.com/tterb/Urban-Dictionary-Therapy/archive/1.0.1.tar.gz
Keywords: urban,dictionary,therapy,funny,entertainment,cli
Platform: UNKNOWN
Classifier: Development Status :: 4 - Beta
Classifier: Programming Language :: Python :: 3
Classifier: License :: OSI Approved :: MIT License
Classifier: Operating System :: OS Independent
Requires-Dist: colorama (==0.4.1)
Requires-Dist: beautifulsoup4 (==4.7.1)
